LICENSE
MANIFEST.in
README.rst
setup.py
example/001-get-uname.gd
example/002-touch-cfg.gd
example/003-run-cmd.gd
example/004-cd-example.gd
example/005-import.gd
example/godo.cfg.py
example/lib/blammo.py
example/lib/blammo.pyc
example/nested/again/001-run.gd
example/notasks/.empty
example/notasks/subnone/.empty
example/tasks-a/show-order.gd
example/tasks-b/show-order.gd
godo/__init__.py
godo/api.py
godo/attrdict.py
godo/main.py
godo/odict.py
godo/task.py
godo.egg-info/PKG-INFO
godo.egg-info/SOURCES.txt
godo.egg-info/dependency_links.txt
godo.egg-info/entry_points.txt
godo.egg-info/top_level.txt