Metadata-Version: 1.0
Name: godo
Version: 0.0.10
Summary: Run some python code in order.
Home-page: http://github.com/davisp/godo.git
Author: Paul J. Davis
Author-email: paul.joseph.davis@gmail.com
License: MIT
Platform: UNKNOWN
Classifier: Development Status :: 4 - Beta
Classifier: Environment :: Console
Classifier: Intended Audience :: Developers
Classifier: License :: OSI Approved :: MIT License
Classifier: Programming Language :: Python
Classifier: Topic :: Software Development :: Build Tools
